BetterHolidays/__init__.py
BetterHolidays/const.py
BetterHolidays/days.py
BetterHolidays/multi.py
BetterHolidays/typing.py
BetterHolidays/utils.py
BetterHolidays/markets/__init__.py
BetterHolidays/markets/cache.py
BetterHolidays/markets/holidays.py
BetterHolidays/markets/market.py
BetterHolidays/markets/nyse.py
better_holidays-0.1.1.dist-info/licenses/LICENSE
tests/__init__.py
tests/test.py
better_holidays-0.1.1.dist-info/METADATA
better_holidays-0.1.1.dist-info/WHEEL
better_holidays-0.1.1.dist-info/top_level.txt
better_holidays-0.1.1.dist-info/RECORD
