Metadata-Version: 2.4
Name: Better-Holidays
Version: 0.1.1
Summary: A better way to get market holidays
Home-page: https://github.com/Better-Python/better-holidays
Author: R5dan
Keywords: python,better holidays,better,market,stocks,finance,holidays,better python
Classifier: Development Status :: 3 - Alpha
Classifier: Intended Audience :: Developers
Classifier: Programming Language :: Python :: 3
Classifier: Operating System :: MacOS :: MacOS X
Classifier: Operating System :: Microsoft :: Windows
Classifier: Operating System :: POSIX :: Linux
License-File: LICENSE
Requires-Dist: better-md>=0.3.4
Dynamic: author
Dynamic: classifier
Dynamic: description
Dynamic: description-content-type
Dynamic: home-page
Dynamic: keywords
Dynamic: license-file
Dynamic: requires-dist
Dynamic: summary
